COPYING
MANIFEST.in
README.rst
setup.py
aioopenssl/__init__.py
aioopenssl/version.py
aioopenssl.egg-info/PKG-INFO
aioopenssl.egg-info/SOURCES.txt
aioopenssl.egg-info/dependency_links.txt
aioopenssl.egg-info/requires.txt
aioopenssl.egg-info/top_level.txt