Metadata-Version: 1.1
Name: aioopenssl
Version: 0.3.2
Summary: TLS-capable transport using OpenSSL for asyncio
Home-page: https://github.com/horazont/aioopenssl
Author: Jonas Wielicki
Author-email: jonas@wielicki.name
License: Apache 2.0
Keywords: openssl asyncio library transport starttls
Platform: UNKNOWN
Classifier: Development Status :: 3 - Alpha
Classifier: Intended Audience :: Developers
Classifier: Operating System :: POSIX
Classifier: License :: OSI Approved :: Apache Software License
Classifier: Programming Language :: Python :: 3 :: Only
Classifier: Programming Language :: Python :: 3.3
Classifier: Programming Language :: Python :: 3.4
Classifier: Topic :: Communications :: Chat
